modalkit/__init__.py
modalkit/auth.py
modalkit/exceptions.py
modalkit/fast_api.py
modalkit/inference.py
modalkit/iomodel.py
modalkit/logger.py
modalkit/modalapp.py
modalkit/modalutils.py
modalkit/settings.py
modalkit/task_queue.py
modalkit/utils.py
modalkit-0.2.0.dist-info/licenses/LICENSE
modalkit-0.2.0.dist-info/METADATA
modalkit-0.2.0.dist-info/WHEEL
modalkit-0.2.0.dist-info/top_level.txt
modalkit-0.2.0.dist-info/RECORD
