Metadata-Version: 2.4
Name: modalkit
Version: 0.2.0
Summary: A library to package, ship and deploy your ML app
Author-email: Prassanna Ravishankar <me@prassanna.io>
Project-URL: Repository, https://github.com/prassanna-ravishankar/modalkit
Keywords: python
Classifier: Intended Audience :: Developers
Classifier: Programming Language :: Python
Classifier: Programming Language :: Python :: 3
Classifier: Programming Language :: Python :: 3.9
Classifier: Programming Language :: Python :: 3.10
Classifier: Programming Language :: Python :: 3.11
Classifier: Programming Language :: Python :: 3.12
Classifier: Programming Language :: Python :: 3.13
Classifier: Topic :: Software Development :: Libraries :: Python Modules
Requires-Python: <4.0,>=3.9
License-File: LICENSE
Requires-Dist: pydantic-settings-yaml>=0.2.0
Requires-Dist: pydantic>=2
Requires-Dist: python-decouple>=3.8
Requires-Dist: python-json-logger>=2.0.7
Requires-Dist: boto3>=1.35.71
Requires-Dist: fastapi>=0.115.5
Requires-Dist: modal>=0.67.2
Requires-Dist: pydantic-settings-yaml>=0.2.0
Requires-Dist: pydantic-settings>=2.6.1
Requires-Dist: cachetools>=5.5.0
Requires-Dist: boto3-stubs>=1.35.74
Requires-Dist: httpx>=0.28.1
Requires-Dist: taskiq>=0.11.0
Requires-Dist: httpcore>=1.0.9
Requires-Dist: jinja2>=3.1.6
Dynamic: license-file
